dotpla/__init__.py
dotpla/admin.py
dotpla/apps.py
dotpla/middleware.py
dotpla/migrations/__init__.py
dotpla/models.py
dotpla/wagtail_hooks.py
dotpla/wagtail_views.py
dotpla-0.1.0.dist-info/LICENSE
dotpla-0.1.0.dist-info/METADATA
dotpla-0.1.0.dist-info/WHEEL
dotpla-0.1.0.dist-info/RECORD
